pythondata_misc_opentitan
