Metadata-Version: 2.1
Name: pythondata-misc-opentitan
Version: 0.0.post5102
Summary: Python module containing resources files for OpenTitan misc.
Home-page: https://github.com/litex-hub/pythondata-misc-opentitan
Author: LiteX Authors
Author-email: litex@googlegroups.com
License: UNKNOWN
Project-URL: Bug Tracker, https://github.com/litex-hub/pythondata-misc-opentitan/issues
Project-URL: Source Code, https://github.com/litex-hub/pythondata-misc-opentitan
Platform: UNKNOWN
Classifier: Programming Language :: Python :: 3
Classifier: License :: OSI Approved :: Apache Software License
Classifier: Operating System :: OS Independent
Requires-Python: >=3.5
